{
  "packageName": "Sage light switch echostar",
  "author": "TheMaster",
  "releaseNotes":   "Presence bug fix",
  "gitHubUrl": "https://github.com/djdizzyd/hubitat/tree/master/Drivers/zooz",
  "gitHubUrl": "https://github.com/tmastersmart/hubitat-code",
  "payPalUrl": "https://www.paypal.com/paypalme/tmastersat",	
  "version": "2.8.0",
  "dateReleased": "2022-10-28",
  "category":"Control",
  "tags":["Misc. Devices","Buttons","Lights & Switches","Presence & Location","Zigbee"],
  "drivers": [
    {
      "name":"Sage light switch echostar",
      "namespace": "tmastersmart",
      "location": "https://raw.githubusercontent.com/tmastersmart/hubitat-code/main/sage_light_switch.groovy",
      "required": "true",
        "description": "Sage Light Switch driver. With presence and virtual switch,Button support and simulated battery value",
      "id": "d9e1896a-f2e2-483e-b542-d42c43d87998"
    }
    ]
}
